java_features/FeaturesCalculation.py
java_features/__init__.py
java_features/utilities/__init__.py
java_features/utilities/java_raw_tokenizer.py
java_features/utilities/main_utility.py
java_features/utilities/scoring_utility.py
java_features/utilities/stats_scoring_utility.py
java_features-0.1.1.dist-info/LICENSE
java_features-0.1.1.dist-info/METADATA
java_features-0.1.1.dist-info/WHEEL
java_features-0.1.1.dist-info/top_level.txt
java_features-0.1.1.dist-info/RECORD
