Metadata-Version: 2.1
Name: java_features
Version: 0.1.1
Summary: This package contains java code similarity features calculation
Home-page: https://github.com/tomytw/java-features
Author: Tomy Widjaja
Author-email: tomywid77@gmail.com
Classifier: Programming Language :: Python :: 3.7
Classifier: Programming Language :: Java
Classifier: License :: OSI Approved :: MIT License
Classifier: Topic :: Scientific/Engineering :: Artificial Intelligence
Classifier: Topic :: Text Processing :: General
Classifier: Topic :: Utilities
Requires-Python: >=3.7
License-File: LICENSE
